{
    "module_type": "et_pb_map_pin",
    "label": "Map Pin",
    "category": "media",
    "has_children": false,
    "child_type": null,
    "description": "A single map pin placed on a Map parent module with title and content for its info window.",
    "natural_language_aliases": ["map pin", "marker", "map marker", "pin"],
    "tabs": {
        "general": {
            "toggles": {
                "main_content": {
                    "label": "Pin",
                    "fields": {
                        "title": {
                            "type": "text",
                            "label": "Title",
                            "default": "",
                            "responsive": false,
                            "hover": false
                        },
                        "pin_address": {
                            "type": "text",
                            "label": "Map Pin Address",
                            "default": "",
                            "responsive": false,
                            "hover": false
                        },
                        "content": {
                            "type": "tiny_mce",
                            "label": "Content",
                            "default": "",
                            "responsive": false,
                            "hover": false
                        }
                    }
                }
            }
        },
        "design": {
            "toggles": {}
        },
        "advanced": {
            "toggles": {
                "css": {
                    "label": "Custom CSS",
                    "fields": {
                        "module_class": {
                            "type": "text",
                            "label": "CSS Class",
                            "default": "",
                            "responsive": false,
                            "hover": false
                        },
                        "module_id": {
                            "type": "text",
                            "label": "CSS ID",
                            "default": "",
                            "responsive": false,
                            "hover": false
                        }
                    }
                }
            }
        }
    }
}